gamegrid/__init__.py
gamegrid/_version.py
gamegrid/gamegrid.py
gamegrid/static/extension.js
gamegrid/static/index.js
gamegrid/static/index.js.map
gamegrid-0.5.0a11.data/data/share/jupyter/nbextensions/gamegrid/extension.js
gamegrid-0.5.0a11.data/data/share/jupyter/nbextensions/gamegrid/index.js
gamegrid-0.5.0a11.data/data/share/jupyter/nbextensions/gamegrid/index.js.map
gamegrid-0.5.0a11.dist-info/DESCRIPTION.rst
gamegrid-0.5.0a11.dist-info/METADATA
gamegrid-0.5.0a11.dist-info/RECORD
gamegrid-0.5.0a11.dist-info/WHEEL
gamegrid-0.5.0a11.dist-info/metadata.json
gamegrid-0.5.0a11.dist-info/top_level.txt
